pythOnmarg/__init__.py
pythOnmarg/dataDownload.py
pythonmarg-0.0.1.dist-info/METADATA
pythonmarg-0.0.1.dist-info/WHEEL
pythonmarg-0.0.1.dist-info/licenses/LICENSE
pythonmarg-0.0.1.dist-info/RECORD
