Metadata-Version: 2.3
Name: pythOnmarg
Version: 0.0.1
Summary: A package for accessing and working with the Ontario Marginalization Index.
Author-email: William Conley <william@cconley.ca>
License-File: LICENSE
Classifier: License :: OSI Approved :: GNU General Public License v3 or later (GPLv3+)
Classifier: Operating System :: OS Independent
Classifier: Programming Language :: Python :: 3
Requires-Python: >=3.9
Requires-Dist: geopandas
Requires-Dist: pandas
Requires-Dist: xlrd
